Flask_Tracy-0.1.3.dist-info/DESCRIPTION.rst
Flask_Tracy-0.1.3.dist-info/METADATA
Flask_Tracy-0.1.3.dist-info/RECORD
Flask_Tracy-0.1.3.dist-info/WHEEL
Flask_Tracy-0.1.3.dist-info/metadata.json
Flask_Tracy-0.1.3.dist-info/top_level.txt
flask_tracy/.base.py.swo
flask_tracy/.base.py.swp
flask_tracy/__init__.py
flask_tracy/base.py
flask_tracy/__pycache__/__init__.cpython-34.pyc
flask_tracy/__pycache__/__init__.cpython-35.pyc
flask_tracy/__pycache__/base.cpython-34.pyc
flask_tracy/__pycache__/base.cpython-35.pyc
flask_tracy/__pycache__/servers.cpython-34.pyc
